MANIFEST.in
setup.py
nagaram/__init__.py
nagaram/anagrams.py
nagaram/cmdline.py
nagaram/scrabble.py
nagaram.egg-info/PKG-INFO
nagaram.egg-info/SOURCES.txt
nagaram.egg-info/dependency_links.txt
nagaram.egg-info/entry_points.txt
nagaram.egg-info/not-zip-safe
nagaram.egg-info/top_level.txt
nagaram/wordlists/sowpods.txt
nagaram/wordlists/twl.txt
test/test_anagrams.py
test/test_cmdline.py
test/test_scrabble.py