Metadata-Version: 1.1
Name: nagaram
Version: 0.3.8
Summary: Scrabble anagram finder
Home-page: https://github.com/a-tal/nagaram
Author: Adam Talsma
Author-email: adam@talsma.ca
License: BSD
Download-URL: https://github.com/a-tal/nagaram
Platform: UNKNOWN
Classifier: Development Status :: 5 - Production/Stable
Classifier: Environment :: Console
Classifier: Intended Audience :: End Users/Desktop
Classifier: License :: OSI Approved :: BSD License
Classifier: Operating System :: OS Independent
Classifier: Topic :: Games/Entertainment
Classifier: Topic :: Utilities
